jsontableschema_pandas/VERSION
jsontableschema_pandas/__init__.py
jsontableschema_pandas/mappers.py
jsontableschema_pandas/storage.py
jsontableschema_pandas-0.5.0.dist-info/DESCRIPTION.rst
jsontableschema_pandas-0.5.0.dist-info/METADATA
jsontableschema_pandas-0.5.0.dist-info/RECORD
jsontableschema_pandas-0.5.0.dist-info/WHEEL
jsontableschema_pandas-0.5.0.dist-info/metadata.json
jsontableschema_pandas-0.5.0.dist-info/top_level.txt
