Metadata-Version: 2.0
Name: jsontableschema-pandas
Version: 0.5.0
Summary: Generate Pandas data frames, load and extract data, based on JSON Table Schema descriptors.
Home-page: https://github.com/frictionlessdata/jsontableschema-pandas-py
Author: Open Knowledge Foundation
Author-email: info@okfn.org
License: LGPLv3+
Keywords: frictionless data,datapackage,pandas
Platform: UNKNOWN
Classifier: Development Status :: 4 - Beta
Classifier: Intended Audience :: Developers
Classifier: Intended Audience :: Science/Research
Classifier: License :: OSI Approved :: GNU Lesser General Public License v3 or later (LGPLv3+)
Classifier: Operating System :: OS Independent
Classifier: Programming Language :: Python :: 2
Classifier: Programming Language :: Python :: 2.7
Classifier: Programming Language :: Python :: 3
Classifier: Programming Language :: Python :: 3.4
Classifier: Programming Language :: Python :: 3.5
Classifier: Topic :: Scientific/Engineering :: Information Analysis
Classifier: Topic :: Software Development :: Libraries :: Python Modules
Requires-Dist: jsontableschema (>=0.7,<2.0)
Requires-Dist: pandas (>=0.18,<2.0)
Requires-Dist: six (>=1.9,<2.0)
Requires-Dist: tabulator (>=0.7,<2.0)
Provides-Extra: develop
Requires-Dist: pylama; extra == 'develop'
Requires-Dist: tox; extra == 'develop'
